xtremes/__init__.py
xtremes/biascorrection.py
xtremes/biascorrection_erroneous.py
xtremes/biascorrection_topt.py
xtremes/bootstrap.py
xtremes/miscellaneous.py
xtremes/topt.py
xtremes-0.3.6.dist-info/METADATA
xtremes-0.3.6.dist-info/WHEEL
xtremes-0.3.6.dist-info/RECORD
