Metadata-Version: 2.4
Name: xtremes
Version: 0.3.6
Summary: Some utilities to perform Extreme Value Analysis
Project-URL: Homepage, https://github.com/haufse/xtremes
Project-URL: Repository, https://github.com/haufse/xtremes
Project-URL: Documentation, https://xtremes.readthedocs.io/en/latest/
Author-email: Erik Haufs <erik.haufs@rub.de>
Classifier: License :: OSI Approved :: MIT License
Classifier: Operating System :: OS Independent
Classifier: Programming Language :: Python :: 3
Requires-Python: >=3.6
Requires-Dist: matplotlib
Requires-Dist: numpy
Requires-Dist: pynverse
Requires-Dist: scipy
Requires-Dist: tqdm
